mcp_clickhouse/__init__.py
mcp_clickhouse/instructions.py
mcp_clickhouse/main.py
mcp_clickhouse/mcp_env.py
mcp_clickhouse/mcp_server.py
mcp_clickhouse/prompts/instructions.md
ff_mcp_clickhouse-0.1.8.dist-info/METADATA
ff_mcp_clickhouse-0.1.8.dist-info/WHEEL
ff_mcp_clickhouse-0.1.8.dist-info/entry_points.txt
ff_mcp_clickhouse-0.1.8.dist-info/licenses/LICENSE
ff_mcp_clickhouse-0.1.8.dist-info/RECORD
